ageless/__init__.py
ageless/query.py
ageless/serializable.py
ageless/service.py
ageless/criterion/__init__.py
ageless/criterion/edge.py
ageless/criterion/entity.py
ageless/criterion/path.py
ageless/criterion/q.py
ageless/criterion/vertex.py
ageless/entites/__init__.py
ageless/entites/base.py
ageless/entites/edge.py
ageless/entites/property.py
ageless/entites/vertext.py
ageless/operators/__init__.py
ageless/operators/base.py
ageless/operators/contains.py
ageless/operators/ends_with.py
ageless/operators/eq.py
ageless/operators/is_not_null.py
ageless/operators/is_null.py
ageless/operators/manager.py
ageless/operators/ne.py
ageless/operators/raw.py
ageless/operators/regex.py
ageless/operators/runtime.py
ageless/operators/starts_with.py
ageless/operators/value.py
ageless-0.1.dist-info/METADATA
ageless-0.1.dist-info/WHEEL
ageless-0.1.dist-info/top_level.txt
ageless-0.1.dist-info/RECORD
